gcp_jupyterlab_shared/__init__.py
gcp_jupyterlab_shared/handlers.py
gcp_jupyterlab_shared/handlers_test.py
gcp_jupyterlab_shared/test_data.py
gcp_jupyterlab_shared-1.0.8.data/data/etc/jupyter/jupyter_notebook_config.d/gcp_jupyterlab_shared.json
gcp_jupyterlab_shared-1.0.8.dist-info/METADATA
gcp_jupyterlab_shared-1.0.8.dist-info/WHEEL
gcp_jupyterlab_shared-1.0.8.dist-info/top_level.txt
gcp_jupyterlab_shared-1.0.8.dist-info/RECORD
