Metadata-Version: 2.1
Name: gcp-jupyterlab-shared
Version: 1.0.8
Summary: Shared libraries for JupyterLab extensions
Home-page: https://github.com/GoogleCloudPlatform/jupyter-extensions
License: Apache License 2.0
Platform: UNKNOWN
Requires-Python: >=3.6
Requires-Dist: google-auth (>=1.6.3)
Requires-Dist: jupyterlab (~=1.2.0)
Requires-Dist: requests (>=2.22.0)
